README.rst
setup.py
lxdapi/__init__.py
lxdapi/api.py
lxdapi/lxd.py
lxdapi/shortcuts.py
lxdapi.egg-info/PKG-INFO
lxdapi.egg-info/SOURCES.txt
lxdapi.egg-info/dependency_links.txt
lxdapi.egg-info/not-zip-safe
lxdapi.egg-info/requires.txt
lxdapi.egg-info/top_level.txt