Metadata-Version: 1.1
Name: lxdapi
Version: 0.0.1
Summary: Low-level alternative to pylxd
Home-page: https://github.com/novafloss/lxdapi
Author: James Pic
Author-email: jamespic@gmail.com
License: UNKNOWN
Platform: UNKNOWN
Classifier: Intended Audience :: Developers
Classifier: License :: OSI Approved :: ISC License (ISCL)
Classifier: Programming Language :: Python
Classifier: Programming Language :: Python :: 2.7
Classifier: Programming Language :: Python :: 3.4
Classifier: Programming Language :: Python :: 3.5
